github_review_app.py
GhReviewer-0.1.0.dist-info/METADATA
GhReviewer-0.1.0.dist-info/WHEEL
GhReviewer-0.1.0.dist-info/entry_points.txt
GhReviewer-0.1.0.dist-info/top_level.txt
GhReviewer-0.1.0.dist-info/RECORD
